{
  "total_signed_deals": 4531,
  "unique_firms": 132,
  "firm_signups": {
    "KP Injury Law": 46,
    "Chalik & Chalik": 250,
    "KJ Injury Law": 827,
    "Fang Accident Lawyers": 252,
    "Richard Harris Law Firm": 4,
    "Loncar Lyon Jenkins": 343,
    "Geoff McDonald & Associates": 13,
    "Boston Auto Law": 28,
    "The Major Law Firm": 59,
    "Brent Coon & Associates": 10,
    "JRE Injury Law": 76,
    "Marker Law": 27,
    "Sweet Law": 69,
    "Pencheff & Fraley": 111,
    "Green Law Group": 27,
    "Astrix Law": 158,
    "Larry H. Parker": 20,
    "Oakwood Legal Group": 20,
    "Bernard Law Group": 28,
    "Levine Law": 30,
    "Irons & Irons": 23,
    "Law Offices of Luke T. Moreau": 12,
    "Sargon Law Group": 9,
    "AK Law Firm": 76,
    "Gibson Hill Personal Injury": 6,
    "J. Hartley Law": 2,
    "Malik Law": 3,
    "Klenofsky & Steward": 21,
    "Hilley & Solis": 197,
    "The Brown Firm": 24,
    "LawyerUp": 5,
    "Edward Law Group": 214,
    "KC Accident Injury Attorneys": 34,
    "Schilling & Silvers": 31,
    "Gibbins Law": 79,
    "Campione Law": 24,
    "Dan Chiacchia Injury Attorneys": 16,
    "Vanstone Injury Law": 1,
    "Kronos Law Firm": 2,
    "Loncar Lyon Jenkins (clone) (clone)": 1,
    "Law Office of Shane R. Kadlec": 33,
    "California Attorney Group": 8,
    "Premise \u2013 VanStone Injury Law": 1,
    "Auto Accident -": 1,
    "KJ Injury Law (clone)": 2,
    "Campione Law (clone)": 1,
    "Loncar Lyon Jenkins (clone)": 1,
    "The Law Office of Daniel A. Brown": 22,
    "Dan Chiacchia Injury Attorneys (clone)": 1,
    "Chalik & Chalik (clone)": 2,
    "Abels & Annes": 18,
    "Titan Law Firm": 3,
    "Pencheff & Fraley (clone)": 1,
    "The Shamsi Law Firm": 1,
    "Hilley & Solis (clone)": 1,
    "KP Law Firm": 8,
    "The Law Offices of Daniel A. Brown": 1,
    "Hollander Law Firm": 6,
    "Isaacs and Isaacs": 66,
    "Dworkin & Maciariello": 173,
    "Wilk Law": 231,
    "Russo Firm": 44,
    "Pittman, Dutton, Hellums, Bradley & Mann": 2,
    "Mott & Moffett LLP": 10,
    "Farah & Farah": 51,
    "Maison Law": 49,
    "Wernik Law": 3,
    "Jacoby & Meyers": 152,
    "Armada Law": 40,
    "Big Auto Accident Attorneys": 8,
    "Hach & Rose": 3,
    "Personal Injury Attorney Lawyer": 3,
    "MVP Accident Attorneys": 5,
    "Carabin Shaw": 118,
    "McCarthy and Associates": 26,
    "Oaks Law Firm": 3,
    "McCormick Law": 9,
    "Setareh Law": 4,
    "Ladva Law Firm": 3,
    "Mendez & Sanchez Law": 1,
    "Umansky Law Firm": 1,
    "Jalal Abdallah Law": 13,
    "The Law Offices of David A. Kadzai": 6,
    "Law Offices of Bobby Garcia": 3,
    "Law Offices of Paul Levin": 4,
    "Stalwart Law": 30,
    "Rivers Law Group": 29,
    "Ace Lakhani Law Firm": 2,
    "Magazine Law Group": 2,
    "Kaufman & Lynd": 3,
    "J&Y Law": 4,
    "Duncan Law Firm": 8,
    "Law Offices Of Marc J. Shefman": 7,
    "Burrow & Associates": 4,
    "Shamieh Law": 47,
    "Ryan Hughes Law": 8,
    "Titus Law Firm": 1,
    "Trust Guss Injury Lawyers": 2,
    "Ladah Law Firm": 14,
    "Brighter Day Law": 5,
    "Cameron Law": 2,
    "Bennerotte & Associates": 2,
    "Goldenzweig Law Group": 6,
    "Levin, Rojas, Camassar & Reck": 1,
    "Thompson Law (Axon)": 1,
    "Rudin Law": 7,
    "Orsatti Legal Group": 2,
    "The Taylor Law Firm": 6,
    "Maricic Law Firm": 5,
    "Harlin Parker Attorneys": 1,
    "The Martin Law Firm": 3,
    "The Law Offices Of Eric R. Bernstein": 2,
    "Carr & Carr": 2,
    "Law Offices of David P. Kashani": 1,
    "Le Blanc Law Firm": 1,
    "Pinnacle LLP": 1,
    "JT Legal Group": 2,
    "Ibay Law Group": 3,
    "Evans / Reilley": 4,
    "Pansini & Pizzica": 3,
    "Zanes Law Injury Lawyers": 11,
    "Innovate Legal Group": 2,
    "Farah Law Group": 3,
    "Viles & Beckman": 1,
    "Law Offices Of James Perrin": 1,
    "Starpoint Law": 1,
    "Astrix Law (clone)": 1,
    "Berman Law Group": 2,
    "Shield Law Group": 4,
    "D. Miller & Associates": 2,
    "Lowe Law Firm": 2,
    "Law Offices of Jack Cruz-Silvestre": 2
  }
}