{
  "total_signed_deals": 6420,
  "unique_firms": 144,
  "firm_signups": {
    "KP Injury Law": 46,
    "Chalik & Chalik": 332,
    "KJ Injury Law": 1183,
    "Fang Accident Lawyers": 285,
    "Richard Harris Law Firm": 8,
    "Loncar Lyon Jenkins": 428,
    "Geoff McDonald & Associates": 17,
    "Boston Auto Law": 42,
    "The Major Law Firm": 89,
    "Brent Coon & Associates": 27,
    "JRE Injury Law": 88,
    "Marker Law": 36,
    "Sweet Law": 118,
    "Pencheff & Fraley": 158,
    "Green Law Group": 44,
    "Astrix Law": 164,
    "Larry H. Parker": 22,
    "Oakwood Legal Group": 20,
    "Bernard Law Group": 34,
    "Levine Law": 50,
    "Irons & Irons": 28,
    "Law Offices of Luke T. Moreau": 19,
    "Sargon Law Group": 11,
    "AK Law Firm": 103,
    "Gibson Hill Personal Injury": 12,
    "J. Hartley Law": 2,
    "Malik Law": 3,
    "Klenofsky & Steward": 23,
    "Hilley & Solis": 279,
    "The Brown Firm": 39,
    "LawyerUp": 13,
    "Edward Law Group": 392,
    "Schilling & Silvers": 30,
    "Campione Law": 24,
    "Dan Chiacchia Injury Attorneys": 16,
    "KC Accident Injury Attorneys": 30,
    "Vanstone Injury Law": 1,
    "Gibbins Law": 108,
    "Kronos Law Firm": 2,
    "Loncar Lyon Jenkins (clone) (clone)": 1,
    "Law Office of Shane R. Kadlec": 33,
    "California Attorney Group": 8,
    "Premise \u2013 VanStone Injury Law": 1,
    "Auto Accident -": 1,
    "KJ Injury Law (clone)": 2,
    "Campione Law (clone)": 1,
    "Loncar Lyon Jenkins (clone)": 1,
    "The Law Office of Daniel A. Brown": 22,
    "Dan Chiacchia Injury Attorneys (clone)": 1,
    "Chalik & Chalik (clone)": 2,
    "Abels & Annes": 35,
    "Titan Law Firm": 3,
    "Pencheff & Fraley (clone)": 1,
    "The Shamsi Law Firm": 2,
    "Hilley & Solis (clone)": 1,
    "KP Law Firm": 8,
    "The Law Offices of Daniel A. Brown": 1,
    "Hollander Law Firm": 6,
    "Isaacs and Isaacs": 77,
    "Dworkin & Maciariello": 229,
    "Wilk Law": 364,
    "Russo Firm": 54,
    "Pittman, Dutton, Hellums, Bradley & Mann": 2,
    "Mott & Moffett LLP": 12,
    "Farah & Farah": 71,
    "Maison Law": 87,
    "Wernik Law": 4,
    "Jacoby & Meyers": 268,
    "Armada Law": 53,
    "Big Auto Accident Attorneys": 10,
    "Hach & Rose": 3,
    "Personal Injury Attorney Lawyer": 4,
    "MVP Accident Attorneys": 5,
    "Carabin Shaw": 206,
    "McCarthy and Associates": 30,
    "Oaks Law Firm": 4,
    "McCormick Law": 10,
    "Setareh Law": 5,
    "Ladva Law Firm": 3,
    "Mendez & Sanchez Law": 1,
    "Umansky Law Firm": 1,
    "Jalal Abdallah Law": 17,
    "The Law Offices of David A. Kadzai": 13,
    "Law Offices of Bobby Garcia": 3,
    "Law Offices of Paul Levin": 5,
    "Stalwart Law": 47,
    "Rivers Law Group": 42,
    "Ace Lakhani Law Firm": 2,
    "Magazine Law Group": 2,
    "Kaufman & Lynd": 6,
    "J&Y Law": 7,
    "Duncan Law Firm": 11,
    "Law Offices Of Marc J. Shefman": 12,
    "Burrow & Associates": 7,
    "Shamieh Law": 99,
    "Ryan Hughes Law": 10,
    "Titus Law Firm": 1,
    "Trust Guss Injury Lawyers": 4,
    "Ladah Law Firm": 30,
    "Brighter Day Law": 5,
    "Cameron Law": 4,
    "Bennerotte & Associates": 3,
    "Goldenzweig Law Group": 13,
    "Levin, Rojas, Camassar & Reck": 1,
    "Thompson Law (Axon)": 1,
    "Rudin Law": 12,
    "Orsatti Legal Group": 3,
    "The Taylor Law Firm": 15,
    "Maricic Law Firm": 5,
    "Harlin Parker Attorneys": 1,
    "The Martin Law Firm": 9,
    "The Law Offices Of Eric R. Bernstein": 3,
    "Carr & Carr": 2,
    "Law Offices of David P. Kashani": 1,
    "Le Blanc Law Firm": 3,
    "Pinnacle LLP": 5,
    "JT Legal Group": 2,
    "Ibay Law Group": 4,
    "Evans / Reilley": 6,
    "Pansini & Pizzica": 3,
    "Zanes Law Injury Lawyers": 20,
    "Innovate Legal Group": 8,
    "Farah Law Group": 10,
    "Viles & Beckman": 5,
    "Law Offices Of James Perrin": 2,
    "Starpoint Law": 2,
    "Shield Law Group": 10,
    "Law Firm Ocala": 1,
    "Edward M. Bernstein & Associates": 2,
    "Durham Law Group": 4,
    "Berman Law Group": 4,
    "D. Miller & Associates": 4,
    "Law Firm of Roberto L. Sanchez": 3,
    "Lowe Law Firm": 5,
    "Halvorsen Klote Davis": 1,
    "Hammack Law Firm": 1,
    "Four Rivers Law Firm": 1,
    "High Stakes Injury Law": 2,
    "Whalen Injury Lawyers": 1,
    "Balfour Emonet Law Firm": 2,
    "Co & Co": 3,
    "Adebayo Law": 1,
    "Astrix Law (clone)": 1,
    "Law Offices of Jack Cruz-Silvestre": 2
  }
}