{
  "total_signed_deals": 8549,
  "unique_firms": 153,
  "firm_signups": {
    "KP Injury Law": 50,
    "Chalik & Chalik": 445,
    "KJ Injury Law": 1534,
    "Fang Accident Lawyers": 394,
    "Richard Harris Law Firm": 12,
    "Loncar Lyon Jenkins": 603,
    "Geoff McDonald & Associates": 25,
    "Boston Auto Law": 56,
    "The Major Law Firm": 134,
    "Brent Coon & Associates": 49,
    "JRE Injury Law": 122,
    "Marker Law": 56,
    "Sweet Law": 168,
    "Pencheff & Fraley": 251,
    "Green Law Group": 64,
    "Astrix Law": 181,
    "Larry H. Parker": 26,
    "Oakwood Legal Group": 30,
    "Bernard Law Group": 56,
    "Levine Law": 63,
    "Irons & Irons": 48,
    "Law Offices of Luke T. Moreau": 29,
    "Sargon Law Group": 20,
    "AK Law Firm": 143,
    "Gibson Hill Personal Injury": 19,
    "J. Hartley Law": 1,
    "Malik Law": 4,
    "Klenofsky & Steward": 32,
    "Hilley & Solis": 378,
    "The Brown Firm": 52,
    "LawyerUp": 18,
    "Edward Law Group": 548,
    "Portner & Shure": 14,
    "JRE Injury": 2,
    "KC Accident Injury Attorneys": 55,
    "The Roth Firm": 1,
    "GGL Wins": 6,
    "Disparti Law": 3,
    "Michael M. Day Law Firm": 1,
    "Gibbins Law": 134,
    "Schilling & Silvers": 35,
    "Campione Law": 32,
    "Law Office of Shane R. Kadlec": 34,
    "California Attorney Group": 10,
    "Abels & Annes": 52,
    "Dan Chiacchia Injury Attorneys": 16,
    "Vanstone Injury Law": 1,
    "Kronos Law Firm": 2,
    "Loncar Lyon Jenkins (clone) (clone)": 1,
    "Premise \u2013 VanStone Injury Law": 1,
    "Auto Accident -": 1,
    "KJ Injury Law (clone)": 2,
    "Campione Law (clone)": 1,
    "Loncar Lyon Jenkins (clone)": 1,
    "The Law Office of Daniel A. Brown": 22,
    "Dan Chiacchia Injury Attorneys (clone)": 1,
    "Chalik & Chalik (clone)": 2,
    "Titan Law Firm": 3,
    "Pencheff & Fraley (clone)": 1,
    "The Shamsi Law Firm": 5,
    "Hilley & Solis (clone)": 1,
    "KP Law Firm": 8,
    "The Law Offices of Daniel A. Brown": 1,
    "Hollander Law Firm": 6,
    "Isaacs and Isaacs": 87,
    "Dworkin & Maciariello": 256,
    "Wilk Law": 431,
    "Russo Firm": 64,
    "Pittman, Dutton, Hellums, Bradley & Mann": 2,
    "Mott & Moffett LLP": 18,
    "Farah & Farah": 87,
    "Maison Law": 113,
    "Wernik Law": 5,
    "Jacoby & Meyers": 352,
    "Armada Law": 63,
    "Big Auto Accident Attorneys": 13,
    "Hach & Rose": 3,
    "Personal Injury Attorney Lawyer": 5,
    "MVP Accident Attorneys": 5,
    "Carabin Shaw": 287,
    "McCarthy and Associates": 33,
    "Oaks Law Firm": 4,
    "McCormick Law": 11,
    "Setareh Law": 7,
    "Ladva Law Firm": 3,
    "Mendez & Sanchez Law": 2,
    "Umansky Law Firm": 1,
    "Jalal Abdallah Law": 22,
    "The Law Offices of David A. Kadzai": 21,
    "Law Offices of Bobby Garcia": 3,
    "Law Offices of Paul Levin": 5,
    "Stalwart Law": 63,
    "Rivers Law Group": 60,
    "Ace Lakhani Law Firm": 2,
    "Magazine Law Group": 2,
    "Kaufman & Lynd": 11,
    "J&Y Law": 13,
    "Duncan Law Firm": 12,
    "Law Offices Of Marc J. Shefman": 16,
    "Burrow & Associates": 9,
    "Shamieh Law": 142,
    "Ryan Hughes Law": 12,
    "Titus Law Firm": 1,
    "Trust Guss Injury Lawyers": 6,
    "Ladah Law Firm": 47,
    "Brighter Day Law": 5,
    "Cameron Law": 6,
    "Bennerotte & Associates": 4,
    "Goldenzweig Law Group": 18,
    "Levin, Rojas, Camassar & Reck": 1,
    "Thompson Law (Axon)": 1,
    "Rudin Law": 12,
    "Orsatti Legal Group": 4,
    "The Taylor Law Firm": 16,
    "Maricic Law Firm": 8,
    "Harlin Parker Attorneys": 2,
    "The Martin Law Firm": 10,
    "The Law Offices Of Eric R. Bernstein": 4,
    "Carr & Carr": 2,
    "Law Offices of David P. Kashani": 1,
    "Le Blanc Law Firm": 3,
    "Pinnacle LLP": 5,
    "JT Legal Group": 2,
    "Ibay Law Group": 4,
    "Evans / Reilley": 6,
    "Pansini & Pizzica": 7,
    "Zanes Law Injury Lawyers": 35,
    "Innovate Legal Group": 11,
    "Farah Law Group": 16,
    "Viles & Beckman": 10,
    "Law Offices Of James Perrin": 2,
    "Starpoint Law": 3,
    "Shield Law Group": 12,
    "Law Firm Ocala": 1,
    "Edward M. Bernstein & Associates": 5,
    "Durham Law Group": 4,
    "Berman Law Group": 5,
    "D. Miller & Associates": 6,
    "Law Firm of Roberto L. Sanchez": 7,
    "Lowe Law Firm": 7,
    "Halvorsen Klote Davis": 2,
    "Hammack Law Firm": 2,
    "Four Rivers Law Firm": 2,
    "High Stakes Injury Law": 8,
    "Whalen Injury Lawyers": 6,
    "Balfour Emonet Law Firm": 3,
    "Co & Co": 3,
    "Adebayo Law": 1,
    "Tony S. Kalogerakos, Esq.-Injury Lawyers": 2,
    "Raven Injury Law": 2,
    "Thompson Legal": 1,
    "Astrix Law (clone)": 1,
    "Law Offices of Jack Cruz-Silvestre": 2
  }
}